<?xml version="1.0" standalone="no"?>
<!DOCTYPE imgannotool>
<imgannotooldata>
<header>
<creator>Iiris</creator>
<software version="0.2">MVPR/Image Annotation Tool http://www.it.lut.fi/project/imageret/imgannotool/</software>
<affiliation>ImageRet Project, Machine Vision and Pattern Recognition Research Group, Lappeenranta University of Technology, P.O.Box 20, 53851 Lappeenranta, Finland</affiliation>
<copyrightnotice>Restricted academic license, see http://www.it.lut.fi/project/imageret/</copyrightnotice>
</header>
<markinglist>
<marking><circleregion><centroid><coords2d>1155,472</coords2d></centroid><radius direction="x">113</radius></circleregion><representativepoint><coords2d>1104,472</coords2d></representativepoint><confidencelevel>High</confidencelevel><markingtype>Disc</markingtype></marking>
<marking><polygonregion><centroid><coords2d>515,400</coords2d></centroid><coords2d>465,452</coords2d><coords2d>503,456</coords2d><coords2d>543,455</coords2d><coords2d>582,449</coords2d><coords2d>582,400</coords2d><coords2d>578,363</coords2d><coords2d>555,327</coords2d><coords2d>527,325</coords2d><coords2d>510,358</coords2d><coords2d>513,381</coords2d><coords2d>488,387</coords2d><coords2d>455,382</coords2d><coords2d>440,411</coords2d><coords2d>465,452</coords2d></polygonregion><representativepoint><coords2d>543,418</coords2d></representativepoint><confidencelevel>High</confidencelevel><markingtype>Hard_exudates</markingtype></marking>
<marking><polygonregion><centroid><coords2d>319,679</coords2d></centroid><coords2d>391,666</coords2d><coords2d>407,639</coords2d><coords2d>411,605</coords2d><coords2d>396,569</coords2d><coords2d>396,511</coords2d><coords2d>385,471</coords2d><coords2d>369,405</coords2d><coords2d>333,415</coords2d><coords2d>305,452</coords2d><coords2d>279,480</coords2d><coords2d>222,493</coords2d><coords2d>188,482</coords2d><coords2d>167,510</coords2d><coords2d>173,558</coords2d><coords2d>138,591</coords2d><coords2d>113,616</coords2d><coords2d>120,649</coords2d><coords2d>133,684</coords2d><coords2d>158,728</coords2d><coords2d>178,769</coords2d><coords2d>202,804</coords2d><coords2d>228,839</coords2d><coords2d>261,889</coords2d><coords2d>302,922</coords2d><coords2d>349,937</coords2d><coords2d>404,935</coords2d><coords2d>426,918</coords2d><coords2d>410,875</coords2d><coords2d>399,826</coords2d><coords2d>403,779</coords2d><coords2d>455,784</coords2d><coords2d>486,779</coords2d><coords2d>497,744</coords2d><coords2d>480,715</coords2d><coords2d>437,706</coords2d><coords2d>399,707</coords2d><coords2d>391,666</coords2d></polygonregion><representativepoint><coords2d>250,691</coords2d></representativepoint><confidencelevel>High</confidencelevel><markingtype>Haemorrhages</markingtype></marking>
<marking><polygonregion><centroid><coords2d>495,604</coords2d></centroid><coords2d>473,605</coords2d><coords2d>477,623</coords2d><coords2d>501,631</coords2d><coords2d>517,626</coords2d><coords2d>524,600</coords2d><coords2d>511,576</coords2d><coords2d>484,569</coords2d><coords2d>473,605</coords2d></polygonregion><representativepoint><coords2d>501,602</coords2d></representativepoint><confidencelevel>High</confidencelevel><markingtype>Haemorrhages</markingtype></marking>
<marking><polygonregion><centroid><coords2d>1024,820</coords2d></centroid><coords2d>1001,806</coords2d><coords2d>1001,827</coords2d><coords2d>1015,842</coords2d><coords2d>1036,846</coords2d><coords2d>1052,831</coords2d><coords2d>1051,807</coords2d><coords2d>1034,791</coords2d><coords2d>1001,806</coords2d></polygonregion><representativepoint><coords2d>1025,817</coords2d></representativepoint><confidencelevel>High</confidencelevel><markingtype>Haemorrhages</markingtype></marking>
<marking><polygonregion><centroid><coords2d>944,445</coords2d></centroid><coords2d>971,442</coords2d><coords2d>961,419</coords2d><coords2d>935,412</coords2d><coords2d>920,420</coords2d><coords2d>913,442</coords2d><coords2d>914,464</coords2d><coords2d>932,474</coords2d><coords2d>954,471</coords2d><coords2d>972,461</coords2d><coords2d>971,442</coords2d></polygonregion><representativepoint><coords2d>947,443</coords2d></representativepoint><confidencelevel>Medium</confidencelevel><markingtype>Soft_exudates</markingtype></marking>
<marking><polygonregion><centroid><coords2d>732,465</coords2d></centroid><coords2d>752,448</coords2d><coords2d>756,470</coords2d><coords2d>746,483</coords2d><coords2d>726,494</coords2d><coords2d>701,485</coords2d><coords2d>701,467</coords2d><coords2d>715,445</coords2d><coords2d>737,441</coords2d><coords2d>752,448</coords2d></polygonregion><representativepoint><coords2d>734,466</coords2d></representativepoint><confidencelevel>Low</confidencelevel><markingtype>Hard_exudates</markingtype></marking>
<marking><polygonregion><centroid><coords2d>122,786</coords2d></centroid><coords2d>116,815</coords2d><coords2d>142,811</coords2d><coords2d>154,790</coords2d><coords2d>150,763</coords2d><coords2d>124,747</coords2d><coords2d>105,754</coords2d><coords2d>95,779</coords2d><coords2d>100,802</coords2d><coords2d>116,815</coords2d></polygonregion><representativepoint><coords2d>126,781</coords2d></representativepoint><confidencelevel>Low</confidencelevel><markingtype>Haemorrhages</markingtype></marking>
<marking><polygonregion><centroid><coords2d>511,864</coords2d></centroid><coords2d>500,882</coords2d><coords2d>513,884</coords2d><coords2d>528,883</coords2d><coords2d>534,866</coords2d><coords2d>534,841</coords2d><coords2d>523,831</coords2d><coords2d>501,841</coords2d><coords2d>486,853</coords2d><coords2d>486,872</coords2d><coords2d>500,882</coords2d></polygonregion><representativepoint><coords2d>511,861</coords2d></representativepoint><confidencelevel>Low</confidencelevel><markingtype>Haemorrhages</markingtype></marking>
<marking><polygonregion><centroid><coords2d>646,796</coords2d></centroid><coords2d>629,803</coords2d><coords2d>640,811</coords2d><coords2d>650,813</coords2d><coords2d>666,811</coords2d><coords2d>676,804</coords2d><coords2d>675,788</coords2d><coords2d>662,778</coords2d><coords2d>638,776</coords2d><coords2d>622,780</coords2d><coords2d>618,789</coords2d><coords2d>629,803</coords2d></polygonregion><representativepoint><coords2d>656,795</coords2d></representativepoint><confidencelevel>Low</confidencelevel><markingtype>Haemorrhages</markingtype></marking>
</markinglist>
</imgannotooldata>
