<?xml version="1.0" standalone="no"?>
<!DOCTYPE imgannotool SYSTEM "http://www.it.lut.fi/project/imageret/imgannotool/downloads/imgannotool_dataformat_v_0_1.dtd">
<imgannotooldata>
<header>
<creator>Iiris</creator>
<software version="0.2">MVPR/Image Annotation Tool http://www.it.lut.fi/project/imageret/imgannotool/</software>
<affiliation>ImageRet Project, Machine Vision and Pattern Recognition Research Group, Lappeenranta University of Technology, P.O.Box 20, 53851 Lappeenranta, Finland</affiliation>
<copyrightnotice>Restricted academic license, see http://www.it.lut.fi/project/imageret/</copyrightnotice>
</header>
<markinglist>
<marking><circleregion><centroid><coords2d>1165,621</coords2d></centroid><radius direction="x">101</radius></circleregion><representativepoint><coords2d>1142,685</coords2d></representativepoint><confidencelevel>High</confidencelevel><markingtype>Disc</markingtype></marking>
<marking><polygonregion><centroid><coords2d>545,626</coords2d></centroid><coords2d>693,685</coords2d><coords2d>714,738</coords2d><coords2d>685,764</coords2d><coords2d>652,761</coords2d><coords2d>576,815</coords2d><coords2d>517,861</coords2d><coords2d>476,843</coords2d><coords2d>423,843</coords2d><coords2d>362,794</coords2d><coords2d>382,754</coords2d><coords2d>403,738</coords2d><coords2d>377,692</coords2d><coords2d>420,649</coords2d><coords2d>466,616</coords2d><coords2d>484,624</coords2d><coords2d>502,619</coords2d><coords2d>469,601</coords2d><coords2d>441,588</coords2d><coords2d>367,568</coords2d><coords2d>354,540</coords2d><coords2d>380,476</coords2d><coords2d>433,478</coords2d><coords2d>461,491</coords2d><coords2d>504,519</coords2d><coords2d>492,542</coords2d><coords2d>489,565</coords2d><coords2d>504,591</coords2d><coords2d>535,560</coords2d><coords2d>561,534</coords2d><coords2d>584,519</coords2d><coords2d>589,491</coords2d><coords2d>619,489</coords2d><coords2d>617,524</coords2d><coords2d>685,519</coords2d><coords2d>685,542</coords2d><coords2d>635,552</coords2d><coords2d>660,570</coords2d><coords2d>683,593</coords2d><coords2d>724,601</coords2d><coords2d>736,649</coords2d><coords2d>691,662</coords2d><coords2d>691,687</coords2d><coords2d>693,685</coords2d></polygonregion><representativepoint><coords2d>650,726</coords2d></representativepoint><confidencelevel>High</confidencelevel><markingtype>Hard_exudates</markingtype></marking>
<marking><polygonregion><centroid><coords2d>496,445</coords2d></centroid><coords2d>482,435</coords2d><coords2d>474,463</coords2d><coords2d>507,476</coords2d><coords2d>527,450</coords2d><coords2d>515,422</coords2d><coords2d>484,432</coords2d><coords2d>482,435</coords2d></polygonregion><representativepoint><coords2d>499,450</coords2d></representativepoint><confidencelevel>High</confidencelevel><markingtype>Hard_exudates</markingtype></marking>
<marking><polygonregion><centroid><coords2d>383,404</coords2d></centroid><coords2d>369,397</coords2d><coords2d>372,417</coords2d><coords2d>397,427</coords2d><coords2d>413,407</coords2d><coords2d>397,389</coords2d><coords2d>367,394</coords2d><coords2d>369,397</coords2d></polygonregion><representativepoint><coords2d>390,410</coords2d></representativepoint><confidencelevel>High</confidencelevel><markingtype>Hard_exudates</markingtype></marking>
<marking><polygonregion><centroid><coords2d>737,286</coords2d></centroid><coords2d>652,231</coords2d><coords2d>637,259</coords2d><coords2d>678,318</coords2d><coords2d>696,376</coords2d><coords2d>775,387</coords2d><coords2d>777,323</coords2d><coords2d>833,330</coords2d><coords2d>884,300</coords2d><coords2d>841,254</coords2d><coords2d>762,249</coords2d><coords2d>742,226</coords2d><coords2d>655,231</coords2d><coords2d>652,231</coords2d></polygonregion><representativepoint><coords2d>762,282</coords2d></representativepoint><confidencelevel>High</confidencelevel><markingtype>Hard_exudates</markingtype></marking>
<marking><polygonregion><centroid><coords2d>668,175</coords2d></centroid><coords2d>657,139</coords2d><coords2d>627,160</coords2d><coords2d>627,190</coords2d><coords2d>650,198</coords2d><coords2d>691,229</coords2d><coords2d>724,208</coords2d><coords2d>726,170</coords2d><coords2d>657,139</coords2d><coords2d>657,139</coords2d></polygonregion><representativepoint><coords2d>678,193</coords2d></representativepoint><confidencelevel>High</confidencelevel><markingtype>Soft_exudates</markingtype></marking>
<marking><polygonregion><centroid><coords2d>1055,129</coords2d></centroid><coords2d>1058,99</coords2d><coords2d>997,157</coords2d><coords2d>1019,195</coords2d><coords2d>1086,152</coords2d><coords2d>1101,104</coords2d><coords2d>1063,99</coords2d><coords2d>1058,99</coords2d></polygonregion><representativepoint><coords2d>1019,165</coords2d></representativepoint><confidencelevel>High</confidencelevel><markingtype>Soft_exudates</markingtype></marking>
<marking><polygonregion><centroid><coords2d>360,695</coords2d></centroid><coords2d>369,672</coords2d><coords2d>321,695</coords2d><coords2d>344,736</coords2d><coords2d>385,713</coords2d><coords2d>372,680</coords2d><coords2d>369,672</coords2d></polygonregion><representativepoint><coords2d>354,713</coords2d></representativepoint><confidencelevel>High</confidencelevel><markingtype>Hard_exudates</markingtype></marking>
<marking><ellipseregion><centroid><coords2d>571,463</coords2d></centroid><radius direction="x">53</radius><radius direction="y">46</radius><angle>54</angle></ellipseregion><representativepoint><coords2d>553,481</coords2d></representativepoint><confidencelevel>High</confidencelevel><markingtype>Haemorrhages</markingtype></marking>
<marking><ellipseregion><centroid><coords2d>344,65</coords2d></centroid><radius direction="x">71</radius><radius direction="y">56</radius><angle>6</angle></ellipseregion><representativepoint><coords2d>369,58</coords2d></representativepoint><confidencelevel>High</confidencelevel><markingtype>Haemorrhages</markingtype></marking>
<marking><ellipseregion><centroid><coords2d>257,624</coords2d></centroid><radius direction="x">34</radius><radius direction="y">28</radius><angle>107</angle></ellipseregion><representativepoint><coords2d>257,626</coords2d></representativepoint><confidencelevel>High</confidencelevel><markingtype>Haemorrhages</markingtype></marking>
<marking><ellipseregion><centroid><coords2d>127,652</coords2d></centroid><radius direction="x">41</radius><radius direction="y">34</radius><angle>23</angle></ellipseregion><representativepoint><coords2d>120,657</coords2d></representativepoint><confidencelevel>High</confidencelevel><markingtype>Haemorrhages</markingtype></marking>
<marking><ellipseregion><centroid><coords2d>165,524</coords2d></centroid><radius direction="x">45</radius><radius direction="y">37</radius><angle>13</angle></ellipseregion><representativepoint><coords2d>178,524</coords2d></representativepoint><confidencelevel>High</confidencelevel><markingtype>Haemorrhages</markingtype></marking>
<marking><ellipseregion><centroid><coords2d>239,239</coords2d></centroid><radius direction="x">67</radius><radius direction="y">35</radius><angle>137</angle></ellipseregion><representativepoint><coords2d>222,226</coords2d></representativepoint><confidencelevel>High</confidencelevel><markingtype>Haemorrhages</markingtype></marking>
<marking><ellipseregion><centroid><coords2d>336,988</coords2d></centroid><radius direction="x">28</radius><radius direction="y">27</radius><angle>4</angle></ellipseregion><representativepoint><coords2d>331,990</coords2d></representativepoint><confidencelevel>High</confidencelevel><markingtype>Haemorrhages</markingtype></marking>
<marking><ellipseregion><centroid><coords2d>541,941</coords2d></centroid><radius direction="x">18</radius><radius direction="y">16</radius><angle>103</angle></ellipseregion><representativepoint><coords2d>545,949</coords2d></representativepoint><confidencelevel>High</confidencelevel><markingtype>Haemorrhages</markingtype></marking>
<marking><ellipseregion><centroid><coords2d>522,1003</coords2d></centroid><radius direction="x">26</radius><radius direction="y">19</radius><angle>173</angle></ellipseregion><representativepoint><coords2d>524,1001</coords2d></representativepoint><confidencelevel>High</confidencelevel><markingtype>Haemorrhages</markingtype></marking>
<marking><ellipseregion><centroid><coords2d>591,841</coords2d></centroid><radius direction="x">17</radius><radius direction="y">18</radius><angle>77</angle></ellipseregion><representativepoint><coords2d>589,838</coords2d></representativepoint><confidencelevel>High</confidencelevel><markingtype>Haemorrhages</markingtype></marking>
<marking><ellipseregion><centroid><coords2d>338,858</coords2d></centroid><radius direction="x">20</radius><radius direction="y">15</radius><angle>90</angle></ellipseregion><representativepoint><coords2d>337,861</coords2d></representativepoint><confidencelevel>High</confidencelevel><markingtype>Haemorrhages</markingtype></marking>
<marking><circleregion><centroid><coords2d>638,867</coords2d></centroid><radius direction="x">15</radius></circleregion><representativepoint><coords2d>638,868</coords2d></representativepoint><confidencelevel>High</confidencelevel><markingtype>Red_small_dots</markingtype></marking>
<marking><circleregion><centroid><coords2d>411,972</coords2d></centroid><radius direction="x">15</radius></circleregion><representativepoint><coords2d>411,971</coords2d></representativepoint><confidencelevel>High</confidencelevel><markingtype>Red_small_dots</markingtype></marking>
<marking><circleregion><centroid><coords2d>454,988</coords2d></centroid><radius direction="x">11</radius></circleregion><representativepoint><coords2d>455,987</coords2d></representativepoint><confidencelevel>High</confidencelevel><markingtype>Red_small_dots</markingtype></marking>
<marking><circleregion><centroid><coords2d>351,730</coords2d></centroid><radius direction="x">37</radius></circleregion><representativepoint><coords2d>347,727</coords2d></representativepoint><confidencelevel>High</confidencelevel><markingtype>Haemorrhages</markingtype></marking>
<marking><circleregion><centroid><coords2d>480,1097</coords2d></centroid><radius direction="x">30</radius></circleregion><representativepoint><coords2d>487,1096</coords2d></representativepoint><confidencelevel>Low</confidencelevel><markingtype>Soft_exudates</markingtype></marking>
<marking><circleregion><centroid><coords2d>358,482</coords2d></centroid><radius direction="x">15</radius></circleregion><representativepoint><coords2d>357,481</coords2d></representativepoint><confidencelevel>Low</confidencelevel><markingtype>Haemorrhages</markingtype></marking>
<marking><circleregion><centroid><coords2d>235,486</coords2d></centroid><radius direction="x">22</radius></circleregion><representativepoint><coords2d>231,491</coords2d></representativepoint><confidencelevel>Low</confidencelevel><markingtype>Haemorrhages</markingtype></marking>
<marking><circleregion><centroid><coords2d>340,235</coords2d></centroid><radius direction="x">17</radius></circleregion><representativepoint><coords2d>334,234</coords2d></representativepoint><confidencelevel>Low</confidencelevel><markingtype>Red_small_dots</markingtype></marking>
<marking><circleregion><centroid><coords2d>498,59</coords2d></centroid><radius direction="x">23</radius></circleregion><representativepoint><coords2d>497,63</coords2d></representativepoint><confidencelevel>Low</confidencelevel><markingtype>Haemorrhages</markingtype></marking>
<marking><circleregion><centroid><coords2d>698,224</coords2d></centroid><radius direction="x">24</radius></circleregion><representativepoint><coords2d>699,219</coords2d></representativepoint><confidencelevel>High</confidencelevel><markingtype>Haemorrhages</markingtype></marking>
<marking><circleregion><centroid><coords2d>657,199</coords2d></centroid><radius direction="x">17</radius></circleregion><representativepoint><coords2d>659,195</coords2d></representativepoint><confidencelevel>High</confidencelevel><markingtype>Haemorrhages</markingtype></marking>
<marking><circleregion><centroid><coords2d>624,161</coords2d></centroid><radius direction="x">16</radius></circleregion><representativepoint><coords2d>622,160</coords2d></representativepoint><confidencelevel>High</confidencelevel><markingtype>Haemorrhages</markingtype></marking>
<marking><circleregion><centroid><coords2d>931,110</coords2d></centroid><radius direction="x">17</radius></circleregion><representativepoint><coords2d>933,110</coords2d></representativepoint><confidencelevel>High</confidencelevel><markingtype>Red_small_dots</markingtype></marking>
<marking><circleregion><centroid><coords2d>947,171</coords2d></centroid><radius direction="x">30</radius></circleregion><representativepoint><coords2d>943,171</coords2d></representativepoint><confidencelevel>Low</confidencelevel><markingtype>Haemorrhages</markingtype></marking>
<marking><circleregion><centroid><coords2d>827,454</coords2d></centroid><radius direction="x">16</radius></circleregion><representativepoint><coords2d>826,454</coords2d></representativepoint><confidencelevel>Medium</confidencelevel><markingtype>Haemorrhages</markingtype></marking>
<marking><circleregion><centroid><coords2d>639,452</coords2d></centroid><radius direction="x">12</radius></circleregion><representativepoint><coords2d>638,452</coords2d></representativepoint><confidencelevel>Medium</confidencelevel><markingtype>Haemorrhages</markingtype></marking>
<marking><ellipseregion><centroid><coords2d>742,793</coords2d></centroid><radius direction="x">56</radius><radius direction="y">20</radius><angle>149</angle></ellipseregion><representativepoint><coords2d>756,799</coords2d></representativepoint><confidencelevel>Medium</confidencelevel><markingtype>Haemorrhages</markingtype></marking>
<marking><ellipseregion><centroid><coords2d>1032,1017</coords2d></centroid><radius direction="x">21</radius><radius direction="y">15</radius><angle>107</angle></ellipseregion><representativepoint><coords2d>1031,1017</coords2d></representativepoint><confidencelevel>Medium</confidencelevel><markingtype>Red_small_dots</markingtype></marking>
</markinglist>
</imgannotooldata>
